[{"postalCode":"0360171","prefKana":"アオモリケン","address1Kana":"ヒラカワシ","address2Kana":"オグニアセイシヤマ","pref":"青森県","address1":"平川市","address2":"小国浅瀬石山"},{"postalCode":"0360171","prefKana":"アオモリケン","address1Kana":"ヒラカワシ","address2Kana":"オグニカワベ","pref":"青森県","address1":"平川市","address2":"小国川辺"},{"postalCode":"0360171","prefKana":"アオモリケン","address1Kana":"ヒラカワシ","address2Kana":"オグニカワラダ","pref":"青森県","address1":"平川市","address2":"小国川原田"},{"postalCode":"0360171","prefKana":"アオモリケン","address1Kana":"ヒラカワシ","address2Kana":"オグニフカサワ","pref":"青森県","address1":"平川市","address2":"小国深沢"},{"postalCode":"0360171","prefKana":"アオモリケン","address1Kana":"ヒラカワシ","address2Kana":"オグニヤマシタ","pref":"青森県","address1":"平川市","address2":"小国山下"}]