[{"postalCode":"4410312","prefKana":"アイチケン","address1Kana":"トヨカワシ","address2Kana":"ミトチョウニシガタ","pref":"愛知県","address1":"豊川市","address2":"御津町西方"},{"postalCode":"4410312","prefKana":"アイチケン","address1Kana":"トヨカワシ","address2Kana":"ミトチョウニシガタアゲハマ","pref":"愛知県","address1":"豊川市","address2":"御津町西方揚浜"},{"postalCode":"4410312","prefKana":"アイチケン","address1Kana":"トヨカワシ","address2Kana":"ミトチョウニシガタイリハマ","pref":"愛知県","address1":"豊川市","address2":"御津町西方入浜"},{"postalCode":"4410312","prefKana":"アイチケン","address1Kana":"トヨカワシ","address2Kana":"ミトチョウニシガタイリョウダ","pref":"愛知県","address1":"豊川市","address2":"御津町西方井領田"},{"postalCode":"4410312","prefKana":"アイチケン","address1Kana":"トヨカワシ","address2Kana":"ミトチョウニシガタキツネヅカ","pref":"愛知県","address1":"豊川市","address2":"御津町西方狐塚"},{"postalCode":"4410312","prefKana":"アイチケン","address1Kana":"トヨカワシ","address2Kana":"ミトチョウニシガタクサク","pref":"愛知県","address1":"豊川市","address2":"御津町西方九策"},{"postalCode":"4410312","prefKana":"アイチケン","address1Kana":"トヨカワシ","address2Kana":"ミトチョウニシガタゲンノウ","pref":"愛知県","address1":"豊川市","address2":"御津町西方源農"},{"postalCode":"4410312","prefKana":"アイチケン","address1Kana":"トヨカワシ","address2Kana":"ミトチョウニシガタコガイツ","pref":"愛知県","address1":"豊川市","address2":"御津町西方小貝津"},{"postalCode":"4410312","prefKana":"アイチケン","address1Kana":"トヨカワシ","address2Kana":"ミトチョウニシガタシモハマミチ","pref":"愛知県","address1":"豊川市","address2":"御津町西方下浜道"},{"postalCode":"4410312","prefKana":"アイチケン","address1Kana":"トヨカワシ","address2Kana":"ミトチョウニシガタジョウノクチ","pref":"愛知県","address1":"豊川市","address2":"御津町西方常ノ口"},{"postalCode":"4410312","prefKana":"アイチケン","address1Kana":"トヨカワシ","address2Kana":"ミトチョウニシガタチョウダ","pref":"愛知県","address1":"豊川市","address2":"御津町西方長田"},{"postalCode":"4410312","prefKana":"アイチケン","address1Kana":"トヨカワシ","address2Kana":"ミトチョウニシガタトイダ","pref":"愛知県","address1":"豊川市","address2":"御津町西方樋田"},{"postalCode":"4410312","prefKana":"アイチケン","address1Kana":"トヨカワシ","address2Kana":"ミトチョウニシガタナカミチ","pref":"愛知県","address1":"豊川市","address2":"御津町西方中道"},{"postalCode":"4410312","prefKana":"アイチケン","address1Kana":"トヨカワシ","address2Kana":"ミトチョウニシガタナカヤシキ","pref":"愛知県","address1":"豊川市","address2":"御津町西方中屋敷"},{"postalCode":"4410312","prefKana":"アイチケン","address1Kana":"トヨカワシ","address2Kana":"ミトチョウニシガタナシノ","pref":"愛知県","address1":"豊川市","address2":"御津町西方梨野"},{"postalCode":"4410312","prefKana":"アイチケン","address1Kana":"トヨカワシ","address2Kana":"ミトチョウニシガタハマダ","pref":"愛知県","address1":"豊川市","address2":"御津町西方浜田"},{"postalCode":"4410312","prefKana":"アイチケン","address1Kana":"トヨカワシ","address2Kana":"ミトチョウニシガタヒグラシ","pref":"愛知県","address1":"豊川市","address2":"御津町西方日暮"},{"postalCode":"4410312","prefKana":"アイチケン","address1Kana":"トヨカワシ","address2Kana":"ミトチョウニシガタヒロタ","pref":"愛知県","address1":"豊川市","address2":"御津町西方広田"},{"postalCode":"4410312","prefKana":"アイチケン","address1Kana":"トヨカワシ","address2Kana":"ミトチョウニシガタマツモト","pref":"愛知県","address1":"豊川市","address2":"御津町西方松本"},{"postalCode":"4410312","prefKana":"アイチケン","address1Kana":"トヨカワシ","address2Kana":"ミトチョウニシガタミヤナガ","pref":"愛知県","address1":"豊川市","address2":"御津町西方宮長"}]