[{"postalCode":"9696265","prefKana":"フクシマケン","address1Kana":"オオヌマグンアイヅミサトマチ","address2Kana":"ウルシワラキタ","pref":"福島県","address1":"大沼郡会津美里町","address2":"漆原北"},{"postalCode":"9696265","prefKana":"フクシマケン","address1Kana":"オオヌマグンアイヅミサトマチ","address2Kana":"オクラミナミ","pref":"福島県","address1":"大沼郡会津美里町","address2":"御蔵南"},{"postalCode":"9696265","prefKana":"フクシマケン","address1Kana":"オオヌマグンアイヅミサトマチ","address2Kana":"カワゾエ","pref":"福島県","address1":"大沼郡会津美里町","address2":"川添"},{"postalCode":"9696265","prefKana":"フクシマケン","address1Kana":"オオヌマグンアイヅミサトマチ","address2Kana":"タテミナミ","pref":"福島県","address1":"大沼郡会津美里町","address2":"館南"},{"postalCode":"9696265","prefKana":"フクシマケン","address1Kana":"オオヌマグンアイヅミサトマチ","address2Kana":"チョウコウジミナミ","pref":"福島県","address1":"大沼郡会津美里町","address2":"長光寺南"},{"postalCode":"9696265","prefKana":"フクシマケン","address1Kana":"オオヌマグンアイヅミサトマチ","address2Kana":"ロクジゾウ","pref":"福島県","address1":"大沼郡会津美里町","address2":"六地蔵"}]