[{"postalCode":"0295513","prefKana":"イワテケン","address1Kana":"ワガグンニシワガマチ","address2Kana":"カッチ51チワリ","pref":"岩手県","address1":"和賀郡西和賀町","address2":"甲子51地割"},{"postalCode":"0295513","prefKana":"イワテケン","address1Kana":"ワガグンニシワガマチ","address2Kana":"クサイザワ47チワリ","pref":"岩手県","address1":"和賀郡西和賀町","address2":"草井沢47地割"},{"postalCode":"0295513","prefKana":"イワテケン","address1Kana":"ワガグンニシワガマチ","address2Kana":"スギナハタ44チワリ","pref":"岩手県","address1":"和賀郡西和賀町","address2":"杉名畑44地割"},{"postalCode":"0295513","prefKana":"イワテケン","address1Kana":"ワガグンニシワガマチ","address2Kana":"ホンナイ46チワリ","pref":"岩手県","address1":"和賀郡西和賀町","address2":"本内46地割"},{"postalCode":"0295513","prefKana":"イワテケン","address1Kana":"ワガグンニシワガマチ","address2Kana":"ミミドリ49チワリ","pref":"岩手県","address1":"和賀郡西和賀町","address2":"耳取49地割"},{"postalCode":"0295513","prefKana":"イワテケン","address1Kana":"ワガグンニシワガマチ","address2Kana":"モトヤシキ48チワリ","pref":"岩手県","address1":"和賀郡西和賀町","address2":"本屋敷48地割"},{"postalCode":"0295513","prefKana":"イワテケン","address1Kana":"ワガグンニシワガマチ","address2Kana":"ワシノス50チワリ","pref":"岩手県","address1":"和賀郡西和賀町","address2":"鷲之巣50地割"}]